CONTRIBUTING.md
MANIFEST.in
README.rst
setup.py
docs/HISTORY.txt
docs/LICENSE.GPL
docs/LICENSE.txt
eea/__init__.py
eea.progress.workflow.egg-info/PKG-INFO
eea.progress.workflow.egg-info/SOURCES.txt
eea.progress.workflow.egg-info/dependency_links.txt
eea.progress.workflow.egg-info/entry_points.txt
eea.progress.workflow.egg-info/namespace_packages.txt
eea.progress.workflow.egg-info/not-zip-safe
eea.progress.workflow.egg-info/requires.txt
eea.progress.workflow.egg-info/top_level.txt
eea/progress/__init__.py
eea/progress/workflow/README.txt
eea/progress/workflow/__init__.py
eea/progress/workflow/config.py
eea/progress/workflow/configure.zcml
eea/progress/workflow/interfaces.py
eea/progress/workflow/profiles.zcml
eea/progress/workflow/setuphandlers.py
eea/progress/workflow/version.txt
eea/progress/workflow/api/__init__.py
eea/progress/workflow/api/adapters.py
eea/progress/workflow/api/configure.zcml
eea/progress/workflow/browser/__init__.py
eea/progress/workflow/browser/configure.zcml
eea/progress/workflow/exportimport/__init__.py
eea/progress/workflow/exportimport/configure.zcml
eea/progress/workflow/exportimport/progress.py
eea/progress/workflow/locales/__init__.py
eea/progress/workflow/locales/eea.pot
eea/progress/workflow/locales/plone-manual.pot
eea/progress/workflow/locales/update.sh
eea/progress/workflow/locales/bg/LC_MESSAGES/eea.po
eea/progress/workflow/locales/bg/LC_MESSAGES/plone.po
eea/progress/workflow/locales/cs/LC_MESSAGES/eea.po
eea/progress/workflow/locales/cs/LC_MESSAGES/plone.po
eea/progress/workflow/locales/da/LC_MESSAGES/eea.po
eea/progress/workflow/locales/da/LC_MESSAGES/plone.po
eea/progress/workflow/locales/de/LC_MESSAGES/eea.po
eea/progress/workflow/locales/de/LC_MESSAGES/plone.po
eea/progress/workflow/locales/el/LC_MESSAGES/eea.po
eea/progress/workflow/locales/el/LC_MESSAGES/plone.po
eea/progress/workflow/locales/en/LC_MESSAGES/eea.po
eea/progress/workflow/locales/en/LC_MESSAGES/plone.po
eea/progress/workflow/locales/es/LC_MESSAGES/eea.po
eea/progress/workflow/locales/es/LC_MESSAGES/plone.po
eea/progress/workflow/locales/et/LC_MESSAGES/eea.po
eea/progress/workflow/locales/et/LC_MESSAGES/plone.po
eea/progress/workflow/locales/eu/LC_MESSAGES/eea.po
eea/progress/workflow/locales/eu/LC_MESSAGES/plone.po
eea/progress/workflow/locales/fi/LC_MESSAGES/eea.po
eea/progress/workflow/locales/fi/LC_MESSAGES/plone.po
